{"frames":{"sprite1":{"frame":{"x":0,"y":0,"w":75,"h":75},"rotated":false,"trimmed":false,"spriteSourceSize":{"x":0,"y":0,"w":75,"h":75},"sourceSize":{"w":75,"h":75}},"sprite2":{"frame":{"x":75,"y":0,"w":75,"h":75},"rotated":false,"trimmed":false,"spriteSourceSize":{"x":0,"y":0,"w":75,"h":75},"sourceSize":{"w":75,"h":75}},"sprite3":{"frame":{"x":150,"y":0,"w":75,"h":75},"rotated":false,"trimmed":false,"spriteSourceSize":{"x":0,"y":0,"w":75,"h":75},"sourceSize":{"w":75,"h":75}},"sprite4":{"frame":{"x":225,"y":0,"w":75,"h":75},"rotated":false,"trimmed":false,"spriteSourceSize":{"x":0,"y":0,"w":75,"h":75},"sourceSize":{"w":75,"h":75}},"sprite5":{"frame":{"x":300,"y":0,"w":75,"h":75},"rotated":false,"trimmed":false,"spriteSourceSize":{"x":0,"y":0,"w":75,"h":75},"sourceSize":{"w":75,"h":75}},"sprite6":{"frame":{"x":375,"y":0,"w":75,"h":75},"rotated":false,"trimmed":false,"spriteSourceSize":{"x":0,"y":0,"w":75,"h":75},"sourceSize":{"w":75,"h":75}},"sprite7":{"frame":{"x":450,"y":0,"w":75,"h":75},"rotated":false,"trimmed":false,"spriteSourceSize":{"x":0,"y":0,"w":75,"h":75},"sourceSize":{"w":75,"h":75}},"sprite8":{"frame":{"x":525,"y":0,"w":75,"h":75},"rotated":false,"trimmed":false,"spriteSourceSize":{"x":0,"y":0,"w":75,"h":75},"sourceSize":{"w":75,"h":75}},"sprite9":{"frame":{"x":600,"y":0,"w":75,"h":75},"rotated":false,"trimmed":false,"spriteSourceSize":{"x":0,"y":0,"w":75,"h":75},"sourceSize":{"w":75,"h":75}},"sprite10":{"frame":{"x":675,"y":0,"w":75,"h":75},"rotated":false,"trimmed":false,"spriteSourceSize":{"x":0,"y":0,"w":75,"h":75},"sourceSize":{"w":75,"h":75}},"sprite11":{"frame":{"x":750,"y":0,"w":75,"h":75},"rotated":false,"trimmed":false,"spriteSourceSize":{"x":0,"y":0,"w":75,"h":75},"sourceSize":{"w":75,"h":75}},"sprite12":{"frame":{"x":825,"y":0,"w":75,"h":75},"rotated":false,"trimmed":false,"spriteSourceSize":{"x":0,"y":0,"w":75,"h":75},"sourceSize":{"w":75,"h":75}},"sprite13":{"frame":{"x":900,"y":0,"w":75,"h":75},"rotated":false,"trimmed":false,"spriteSourceSize":{"x":0,"y":0,"w":75,"h":75},"sourceSize":{"w":75,"h":75}},"sprite14":{"frame":{"x":975,"y":0,"w":75,"h":75},"rotated":false,"trimmed":false,"spriteSourceSize":{"x":0,"y":0,"w":75,"h":75},"sourceSize":{"w":75,"h":75}},"sprite15":{"frame":{"x":1050,"y":0,"w":75,"h":75},"rotated":false,"trimmed":false,"spriteSourceSize":{"x":0,"y":0,"w":75,"h":75},"sourceSize":{"w":75,"h":75}},"sprite16":{"frame":{"x":1125,"y":0,"w":75,"h":75},"rotated":false,"trimmed":false,"spriteSourceSize":{"x":0,"y":0,"w":75,"h":75},"sourceSize":{"w":75,"h":75}},"sprite17":{"frame":{"x":0,"y":75,"w":75,"h":75},"rotated":false,"trimmed":false,"spriteSourceSize":{"x":0,"y":0,"w":75,"h":75},"sourceSize":{"w":75,"h":75}},"sprite18":{"frame":{"x":75,"y":75,"w":75,"h":75},"rotated":false,"trimmed":false,"spriteSourceSize":{"x":0,"y":0,"w":75,"h":75},"sourceSize":{"w":75,"h":75}},"sprite19":{"frame":{"x":150,"y":75,"w":75,"h":75},"rotated":false,"trimmed":false,"spriteSourceSize":{"x":0,"y":0,"w":75,"h":75},"sourceSize":{"w":75,"h":75}},"sprite20":{"frame":{"x":225,"y":75,"w":75,"h":75},"rotated":false,"trimmed":false,"spriteSourceSize":{"x":0,"y":0,"w":75,"h":75},"sourceSize":{"w":75,"h":75}},"sprite21":{"frame":{"x":300,"y":75,"w":75,"h":75},"rotated":false,"trimmed":false,"spriteSourceSize":{"x":0,"y":0,"w":75,"h":75},"sourceSize":{"w":75,"h":75}},"sprite22":{"frame":{"x":375,"y":75,"w":75,"h":75},"rotated":false,"trimmed":false,"spriteSourceSize":{"x":0,"y":0,"w":75,"h":75},"sourceSize":{"w":75,"h":75}},"sprite23":{"frame":{"x":450,"y":75,"w":75,"h":75},"rotated":false,"trimmed":false,"spriteSourceSize":{"x":0,"y":0,"w":75,"h":75},"sourceSize":{"w":75,"h":75}},"sprite24":{"frame":{"x":525,"y":75,"w":75,"h":75},"rotated":false,"trimmed":false,"spriteSourceSize":{"x":0,"y":0,"w":75,"h":75},"sourceSize":{"w":75,"h":75}},"sprite25":{"frame":{"x":600,"y":75,"w":75,"h":75},"rotated":false,"trimmed":false,"spriteSourceSize":{"x":0,"y":0,"w":75,"h":75},"sourceSize":{"w":75,"h":75}},"sprite26":{"frame":{"x":675,"y":75,"w":75,"h":75},"rotated":false,"trimmed":false,"spriteSourceSize":{"x":0,"y":0,"w":75,"h":75},"sourceSize":{"w":75,"h":75}},"sprite27":{"frame":{"x":750,"y":75,"w":75,"h":75},"rotated":false,"trimmed":false,"spriteSourceSize":{"x":0,"y":0,"w":75,"h":75},"sourceSize":{"w":75,"h":75}},"sprite28":{"frame":{"x":825,"y":75,"w":75,"h":75},"rotated":false,"trimmed":false,"spriteSourceSize":{"x":0,"y":0,"w":75,"h":75},"sourceSize":{"w":75,"h":75}},"sprite29":{"frame":{"x":900,"y":75,"w":75,"h":75},"rotated":false,"trimmed":false,"spriteSourceSize":{"x":0,"y":0,"w":75,"h":75},"sourceSize":{"w":75,"h":75}},"sprite30":{"frame":{"x":975,"y":75,"w":75,"h":75},"rotated":false,"trimmed":false,"spriteSourceSize":{"x":0,"y":0,"w":75,"h":75},"sourceSize":{"w":75,"h":75}},"sprite31":{"frame":{"x":1050,"y":75,"w":75,"h":75},"rotated":false,"trimmed":false,"spriteSourceSize":{"x":0,"y":0,"w":75,"h":75},"sourceSize":{"w":75,"h":75}},"sprite32":{"frame":{"x":1125,"y":75,"w":75,"h":75},"rotated":false,"trimmed":false,"spriteSourceSize":{"x":0,"y":0,"w":75,"h":75},"sourceSize":{"w":75,"h":75}},"sprite33":{"frame":{"x":0,"y":150,"w":75,"h":75},"rotated":false,"trimmed":false,"spriteSourceSize":{"x":0,"y":0,"w":75,"h":75},"sourceSize":{"w":75,"h":75}},"sprite34":{"frame":{"x":75,"y":150,"w":75,"h":75},"rotated":false,"trimmed":false,"spriteSourceSize":{"x":0,"y":0,"w":75,"h":75},"sourceSize":{"w":75,"h":75}},"sprite35":{"frame":{"x":150,"y":150,"w":75,"h":75},"rotated":false,"trimmed":false,"spriteSourceSize":{"x":0,"y":0,"w":75,"h":75},"sourceSize":{"w":75,"h":75}},"sprite36":{"frame":{"x":225,"y":150,"w":75,"h":75},"rotated":false,"trimmed":false,"spriteSourceSize":{"x":0,"y":0,"w":75,"h":75},"sourceSize":{"w":75,"h":75}},"sprite37":{"frame":{"x":300,"y":150,"w":75,"h":75},"rotated":false,"trimmed":false,"spriteSourceSize":{"x":0,"y":0,"w":75,"h":75},"sourceSize":{"w":75,"h":75}},"sprite38":{"frame":{"x":375,"y":150,"w":75,"h":75},"rotated":false,"trimmed":false,"spriteSourceSize":{"x":0,"y":0,"w":75,"h":75},"sourceSize":{"w":75,"h":75}},"sprite39":{"frame":{"x":450,"y":150,"w":75,"h":75},"rotated":false,"trimmed":false,"spriteSourceSize":{"x":0,"y":0,"w":75,"h":75},"sourceSize":{"w":75,"h":75}},"sprite40":{"frame":{"x":525,"y":150,"w":75,"h":75},"rotated":false,"trimmed":false,"spriteSourceSize":{"x":0,"y":0,"w":75,"h":75},"sourceSize":{"w":75,"h":75}},"sprite41":{"frame":{"x":600,"y":150,"w":75,"h":75},"rotated":false,"trimmed":false,"spriteSourceSize":{"x":0,"y":0,"w":75,"h":75},"sourceSize":{"w":75,"h":75}},"sprite42":{"frame":{"x":675,"y":150,"w":75,"h":75},"rotated":false,"trimmed":false,"spriteSourceSize":{"x":0,"y":0,"w":75,"h":75},"sourceSize":{"w":75,"h":75}},"sprite43":{"frame":{"x":750,"y":150,"w":75,"h":75},"rotated":false,"trimmed":false,"spriteSourceSize":{"x":0,"y":0,"w":75,"h":75},"sourceSize":{"w":75,"h":75}},"sprite44":{"frame":{"x":825,"y":150,"w":75,"h":75},"rotated":false,"trimmed":false,"spriteSourceSize":{"x":0,"y":0,"w":75,"h":75},"sourceSize":{"w":75,"h":75}},"sprite45":{"frame":{"x":900,"y":150,"w":75,"h":75},"rotated":false,"trimmed":false,"spriteSourceSize":{"x":0,"y":0,"w":75,"h":75},"sourceSize":{"w":75,"h":75}},"sprite46":{"frame":{"x":975,"y":150,"w":75,"h":75},"rotated":false,"trimmed":false,"spriteSourceSize":{"x":0,"y":0,"w":75,"h":75},"sourceSize":{"w":75,"h":75}},"sprite47":{"frame":{"x":1050,"y":150,"w":75,"h":75},"rotated":false,"trimmed":false,"spriteSourceSize":{"x":0,"y":0,"w":75,"h":75},"sourceSize":{"w":75,"h":75}},"sprite48":{"frame":{"x":1125,"y":150,"w":75,"h":75},"rotated":false,"trimmed":false,"spriteSourceSize":{"x":0,"y":0,"w":75,"h":75},"sourceSize":{"w":75,"h":75}},"sprite49":{"frame":{"x":0,"y":225,"w":75,"h":75},"rotated":false,"trimmed":false,"spriteSourceSize":{"x":0,"y":0,"w":75,"h":75},"sourceSize":{"w":75,"h":75}},"sprite50":{"frame":{"x":75,"y":225,"w":75,"h":75},"rotated":false,"trimmed":false,"spriteSourceSize":{"x":0,"y":0,"w":75,"h":75},"sourceSize":{"w":75,"h":75}},"sprite51":{"frame":{"x":150,"y":225,"w":75,"h":75},"rotated":false,"trimmed":false,"spriteSourceSize":{"x":0,"y":0,"w":75,"h":75},"sourceSize":{"w":75,"h":75}},"sprite52":{"frame":{"x":225,"y":225,"w":75,"h":75},"rotated":false,"trimmed":false,"spriteSourceSize":{"x":0,"y":0,"w":75,"h":75},"sourceSize":{"w":75,"h":75}},"sprite53":{"frame":{"x":300,"y":225,"w":75,"h":75},"rotated":false,"trimmed":false,"spriteSourceSize":{"x":0,"y":0,"w":75,"h":75},"sourceSize":{"w":75,"h":75}},"sprite54":{"frame":{"x":375,"y":225,"w":75,"h":75},"rotated":false,"trimmed":false,"spriteSourceSize":{"x":0,"y":0,"w":75,"h":75},"sourceSize":{"w":75,"h":75}},"sprite55":{"frame":{"x":450,"y":225,"w":75,"h":75},"rotated":false,"trimmed":false,"spriteSourceSize":{"x":0,"y":0,"w":75,"h":75},"sourceSize":{"w":75,"h":75}},"sprite56":{"frame":{"x":525,"y":225,"w":75,"h":75},"rotated":false,"trimmed":false,"spriteSourceSize":{"x":0,"y":0,"w":75,"h":75},"sourceSize":{"w":75,"h":75}},"sprite57":{"frame":{"x":600,"y":225,"w":75,"h":75},"rotated":false,"trimmed":false,"spriteSourceSize":{"x":0,"y":0,"w":75,"h":75},"sourceSize":{"w":75,"h":75}},"sprite58":{"frame":{"x":675,"y":225,"w":75,"h":75},"rotated":false,"trimmed":false,"spriteSourceSize":{"x":0,"y":0,"w":75,"h":75},"sourceSize":{"w":75,"h":75}},"sprite59":{"frame":{"x":750,"y":225,"w":75,"h":75},"rotated":false,"trimmed":false,"spriteSourceSize":{"x":0,"y":0,"w":75,"h":75},"sourceSize":{"w":75,"h":75}},"sprite60":{"frame":{"x":825,"y":225,"w":75,"h":75},"rotated":false,"trimmed":false,"spriteSourceSize":{"x":0,"y":0,"w":75,"h":75},"sourceSize":{"w":75,"h":75}},"sprite61":{"frame":{"x":900,"y":225,"w":75,"h":75},"rotated":false,"trimmed":false,"spriteSourceSize":{"x":0,"y":0,"w":75,"h":75},"sourceSize":{"w":75,"h":75}},"sprite62":{"frame":{"x":975,"y":225,"w":75,"h":75},"rotated":false,"trimmed":false,"spriteSourceSize":{"x":0,"y":0,"w":75,"h":75},"sourceSize":{"w":75,"h":75}},"sprite63":{"frame":{"x":1050,"y":225,"w":75,"h":75},"rotated":false,"trimmed":false,"spriteSourceSize":{"x":0,"y":0,"w":75,"h":75},"sourceSize":{"w":75,"h":75}},"sprite64":{"frame":{"x":1125,"y":225,"w":75,"h":75},"rotated":false,"trimmed":false,"spriteSourceSize":{"x":0,"y":0,"w":75,"h":75},"sourceSize":{"w":75,"h":75}},"sprite65":{"frame":{"x":0,"y":300,"w":75,"h":75},"rotated":false,"trimmed":false,"spriteSourceSize":{"x":0,"y":0,"w":75,"h":75},"sourceSize":{"w":75,"h":75}},"sprite66":{"frame":{"x":75,"y":300,"w":75,"h":75},"rotated":false,"trimmed":false,"spriteSourceSize":{"x":0,"y":0,"w":75,"h":75},"sourceSize":{"w":75,"h":75}},"sprite67":{"frame":{"x":150,"y":300,"w":75,"h":75},"rotated":false,"trimmed":false,"spriteSourceSize":{"x":0,"y":0,"w":75,"h":75},"sourceSize":{"w":75,"h":75}},"sprite68":{"frame":{"x":225,"y":300,"w":75,"h":75},"rotated":false,"trimmed":false,"spriteSourceSize":{"x":0,"y":0,"w":75,"h":75},"sourceSize":{"w":75,"h":75}},"sprite69":{"frame":{"x":300,"y":300,"w":75,"h":75},"rotated":false,"trimmed":false,"spriteSourceSize":{"x":0,"y":0,"w":75,"h":75},"sourceSize":{"w":75,"h":75}},"sprite70":{"frame":{"x":375,"y":300,"w":75,"h":75},"rotated":false,"trimmed":false,"spriteSourceSize":{"x":0,"y":0,"w":75,"h":75},"sourceSize":{"w":75,"h":75}},"sprite71":{"frame":{"x":450,"y":300,"w":75,"h":75},"rotated":false,"trimmed":false,"spriteSourceSize":{"x":0,"y":0,"w":75,"h":75},"sourceSize":{"w":75,"h":75}},"sprite72":{"frame":{"x":525,"y":300,"w":75,"h":75},"rotated":false,"trimmed":false,"spriteSourceSize":{"x":0,"y":0,"w":75,"h":75},"sourceSize":{"w":75,"h":75}},"sprite73":{"frame":{"x":600,"y":300,"w":75,"h":75},"rotated":false,"trimmed":false,"spriteSourceSize":{"x":0,"y":0,"w":75,"h":75},"sourceSize":{"w":75,"h":75}},"sprite74":{"frame":{"x":675,"y":300,"w":75,"h":75},"rotated":false,"trimmed":false,"spriteSourceSize":{"x":0,"y":0,"w":75,"h":75},"sourceSize":{"w":75,"h":75}},"sprite75":{"frame":{"x":750,"y":300,"w":75,"h":75},"rotated":false,"trimmed":false,"spriteSourceSize":{"x":0,"y":0,"w":75,"h":75},"sourceSize":{"w":75,"h":75}},"sprite76":{"frame":{"x":825,"y":300,"w":75,"h":75},"rotated":false,"trimmed":false,"spriteSourceSize":{"x":0,"y":0,"w":75,"h":75},"sourceSize":{"w":75,"h":75}},"sprite77":{"frame":{"x":900,"y":300,"w":75,"h":75},"rotated":false,"trimmed":false,"spriteSourceSize":{"x":0,"y":0,"w":75,"h":75},"sourceSize":{"w":75,"h":75}},"sprite78":{"frame":{"x":975,"y":300,"w":75,"h":75},"rotated":false,"trimmed":false,"spriteSourceSize":{"x":0,"y":0,"w":75,"h":75},"sourceSize":{"w":75,"h":75}},"sprite79":{"frame":{"x":1050,"y":300,"w":75,"h":75},"rotated":false,"trimmed":false,"spriteSourceSize":{"x":0,"y":0,"w":75,"h":75},"sourceSize":{"w":75,"h":75}},"sprite80":{"frame":{"x":1125,"y":300,"w":75,"h":75},"rotated":false,"trimmed":false,"spriteSourceSize":{"x":0,"y":0,"w":75,"h":75},"sourceSize":{"w":75,"h":75}},"sprite81":{"frame":{"x":0,"y":375,"w":75,"h":75},"rotated":false,"trimmed":false,"spriteSourceSize":{"x":0,"y":0,"w":75,"h":75},"sourceSize":{"w":75,"h":75}},"sprite82":{"frame":{"x":75,"y":375,"w":75,"h":75},"rotated":false,"trimmed":false,"spriteSourceSize":{"x":0,"y":0,"w":75,"h":75},"sourceSize":{"w":75,"h":75}},"sprite83":{"frame":{"x":150,"y":375,"w":75,"h":75},"rotated":false,"trimmed":false,"spriteSourceSize":{"x":0,"y":0,"w":75,"h":75},"sourceSize":{"w":75,"h":75}},"sprite84":{"frame":{"x":225,"y":375,"w":75,"h":75},"rotated":false,"trimmed":false,"spriteSourceSize":{"x":0,"y":0,"w":75,"h":75},"sourceSize":{"w":75,"h":75}},"sprite85":{"frame":{"x":300,"y":375,"w":75,"h":75},"rotated":false,"trimmed":false,"spriteSourceSize":{"x":0,"y":0,"w":75,"h":75},"sourceSize":{"w":75,"h":75}},"sprite86":{"frame":{"x":375,"y":375,"w":75,"h":75},"rotated":false,"trimmed":false,"spriteSourceSize":{"x":0,"y":0,"w":75,"h":75},"sourceSize":{"w":75,"h":75}},"sprite87":{"frame":{"x":450,"y":375,"w":75,"h":75},"rotated":false,"trimmed":false,"spriteSourceSize":{"x":0,"y":0,"w":75,"h":75},"sourceSize":{"w":75,"h":75}},"sprite88":{"frame":{"x":525,"y":375,"w":75,"h":75},"rotated":false,"trimmed":false,"spriteSourceSize":{"x":0,"y":0,"w":75,"h":75},"sourceSize":{"w":75,"h":75}},"sprite89":{"frame":{"x":600,"y":375,"w":75,"h":75},"rotated":false,"trimmed":false,"spriteSourceSize":{"x":0,"y":0,"w":75,"h":75},"sourceSize":{"w":75,"h":75}},"sprite90":{"frame":{"x":675,"y":375,"w":75,"h":75},"rotated":false,"trimmed":false,"spriteSourceSize":{"x":0,"y":0,"w":75,"h":75},"sourceSize":{"w":75,"h":75}},"sprite91":{"frame":{"x":750,"y":375,"w":75,"h":75},"rotated":false,"trimmed":false,"spriteSourceSize":{"x":0,"y":0,"w":75,"h":75},"sourceSize":{"w":75,"h":75}},"sprite92":{"frame":{"x":825,"y":375,"w":75,"h":75},"rotated":false,"trimmed":false,"spriteSourceSize":{"x":0,"y":0,"w":75,"h":75},"sourceSize":{"w":75,"h":75}},"sprite93":{"frame":{"x":900,"y":375,"w":75,"h":75},"rotated":false,"trimmed":false,"spriteSourceSize":{"x":0,"y":0,"w":75,"h":75},"sourceSize":{"w":75,"h":75}},"sprite94":{"frame":{"x":975,"y":375,"w":75,"h":75},"rotated":false,"trimmed":false,"spriteSourceSize":{"x":0,"y":0,"w":75,"h":75},"sourceSize":{"w":75,"h":75}},"sprite95":{"frame":{"x":1050,"y":375,"w":75,"h":75},"rotated":false,"trimmed":false,"spriteSourceSize":{"x":0,"y":0,"w":75,"h":75},"sourceSize":{"w":75,"h":75}},"sprite96":{"frame":{"x":1125,"y":375,"w":75,"h":75},"rotated":false,"trimmed":false,"spriteSourceSize":{"x":0,"y":0,"w":75,"h":75},"sourceSize":{"w":75,"h":75}},"sprite97":{"frame":{"x":0,"y":450,"w":75,"h":75},"rotated":false,"trimmed":false,"spriteSourceSize":{"x":0,"y":0,"w":75,"h":75},"sourceSize":{"w":75,"h":75}},"sprite98":{"frame":{"x":75,"y":450,"w":75,"h":75},"rotated":false,"trimmed":false,"spriteSourceSize":{"x":0,"y":0,"w":75,"h":75},"sourceSize":{"w":75,"h":75}},"sprite99":{"frame":{"x":150,"y":450,"w":75,"h":75},"rotated":false,"trimmed":false,"spriteSourceSize":{"x":0,"y":0,"w":75,"h":75},"sourceSize":{"w":75,"h":75}},"sprite100":{"frame":{"x":225,"y":450,"w":75,"h":75},"rotated":false,"trimmed":false,"spriteSourceSize":{"x":0,"y":0,"w":75,"h":75},"sourceSize":{"w":75,"h":75}},"sprite101":{"frame":{"x":300,"y":450,"w":75,"h":75},"rotated":false,"trimmed":false,"spriteSourceSize":{"x":0,"y":0,"w":75,"h":75},"sourceSize":{"w":75,"h":75}},"sprite102":{"frame":{"x":375,"y":450,"w":75,"h":75},"rotated":false,"trimmed":false,"spriteSourceSize":{"x":0,"y":0,"w":75,"h":75},"sourceSize":{"w":75,"h":75}},"sprite103":{"frame":{"x":450,"y":450,"w":75,"h":75},"rotated":false,"trimmed":false,"spriteSourceSize":{"x":0,"y":0,"w":75,"h":75},"sourceSize":{"w":75,"h":75}},"sprite104":{"frame":{"x":525,"y":450,"w":75,"h":75},"rotated":false,"trimmed":false,"spriteSourceSize":{"x":0,"y":0,"w":75,"h":75},"sourceSize":{"w":75,"h":75}},"sprite105":{"frame":{"x":600,"y":450,"w":75,"h":75},"rotated":false,"trimmed":false,"spriteSourceSize":{"x":0,"y":0,"w":75,"h":75},"sourceSize":{"w":75,"h":75}},"sprite106":{"frame":{"x":675,"y":450,"w":75,"h":75},"rotated":false,"trimmed":false,"spriteSourceSize":{"x":0,"y":0,"w":75,"h":75},"sourceSize":{"w":75,"h":75}},"sprite107":{"frame":{"x":750,"y":450,"w":75,"h":75},"rotated":false,"trimmed":false,"spriteSourceSize":{"x":0,"y":0,"w":75,"h":75},"sourceSize":{"w":75,"h":75}},"sprite108":{"frame":{"x":825,"y":450,"w":75,"h":75},"rotated":false,"trimmed":false,"spriteSourceSize":{"x":0,"y":0,"w":75,"h":75},"sourceSize":{"w":75,"h":75}},"sprite109":{"frame":{"x":900,"y":450,"w":75,"h":75},"rotated":false,"trimmed":false,"spriteSourceSize":{"x":0,"y":0,"w":75,"h":75},"sourceSize":{"w":75,"h":75}},"sprite110":{"frame":{"x":975,"y":450,"w":75,"h":75},"rotated":false,"trimmed":false,"spriteSourceSize":{"x":0,"y":0,"w":75,"h":75},"sourceSize":{"w":75,"h":75}},"sprite111":{"frame":{"x":1050,"y":450,"w":75,"h":75},"rotated":false,"trimmed":false,"spriteSourceSize":{"x":0,"y":0,"w":75,"h":75},"sourceSize":{"w":75,"h":75}},"sprite112":{"frame":{"x":1125,"y":450,"w":75,"h":75},"rotated":false,"trimmed":false,"spriteSourceSize":{"x":0,"y":0,"w":75,"h":75},"sourceSize":{"w":75,"h":75}},"sprite113":{"frame":{"x":0,"y":525,"w":75,"h":75},"rotated":false,"trimmed":false,"spriteSourceSize":{"x":0,"y":0,"w":75,"h":75},"sourceSize":{"w":75,"h":75}},"sprite114":{"frame":{"x":75,"y":525,"w":75,"h":75},"rotated":false,"trimmed":false,"spriteSourceSize":{"x":0,"y":0,"w":75,"h":75},"sourceSize":{"w":75,"h":75}},"sprite115":{"frame":{"x":150,"y":525,"w":75,"h":75},"rotated":false,"trimmed":false,"spriteSourceSize":{"x":0,"y":0,"w":75,"h":75},"sourceSize":{"w":75,"h":75}},"sprite116":{"frame":{"x":225,"y":525,"w":75,"h":75},"rotated":false,"trimmed":false,"spriteSourceSize":{"x":0,"y":0,"w":75,"h":75},"sourceSize":{"w":75,"h":75}},"sprite117":{"frame":{"x":300,"y":525,"w":75,"h":75},"rotated":false,"trimmed":false,"spriteSourceSize":{"x":0,"y":0,"w":75,"h":75},"sourceSize":{"w":75,"h":75}},"sprite118":{"frame":{"x":375,"y":525,"w":75,"h":75},"rotated":false,"trimmed":false,"spriteSourceSize":{"x":0,"y":0,"w":75,"h":75},"sourceSize":{"w":75,"h":75}},"sprite119":{"frame":{"x":450,"y":525,"w":75,"h":75},"rotated":false,"trimmed":false,"spriteSourceSize":{"x":0,"y":0,"w":75,"h":75},"sourceSize":{"w":75,"h":75}},"sprite120":{"frame":{"x":525,"y":525,"w":75,"h":75},"rotated":false,"trimmed":false,"spriteSourceSize":{"x":0,"y":0,"w":75,"h":75},"sourceSize":{"w":75,"h":75}},"sprite121":{"frame":{"x":600,"y":525,"w":75,"h":75},"rotated":false,"trimmed":false,"spriteSourceSize":{"x":0,"y":0,"w":75,"h":75},"sourceSize":{"w":75,"h":75}},"sprite122":{"frame":{"x":675,"y":525,"w":75,"h":75},"rotated":false,"trimmed":false,"spriteSourceSize":{"x":0,"y":0,"w":75,"h":75},"sourceSize":{"w":75,"h":75}},"sprite123":{"frame":{"x":750,"y":525,"w":75,"h":75},"rotated":false,"trimmed":false,"spriteSourceSize":{"x":0,"y":0,"w":75,"h":75},"sourceSize":{"w":75,"h":75}},"sprite124":{"frame":{"x":825,"y":525,"w":75,"h":75},"rotated":false,"trimmed":false,"spriteSourceSize":{"x":0,"y":0,"w":75,"h":75},"sourceSize":{"w":75,"h":75}},"sprite125":{"frame":{"x":900,"y":525,"w":75,"h":75},"rotated":false,"trimmed":false,"spriteSourceSize":{"x":0,"y":0,"w":75,"h":75},"sourceSize":{"w":75,"h":75}},"sprite126":{"frame":{"x":975,"y":525,"w":75,"h":75},"rotated":false,"trimmed":false,"spriteSourceSize":{"x":0,"y":0,"w":75,"h":75},"sourceSize":{"w":75,"h":75}},"sprite127":{"frame":{"x":1050,"y":525,"w":75,"h":75},"rotated":false,"trimmed":false,"spriteSourceSize":{"x":0,"y":0,"w":75,"h":75},"sourceSize":{"w":75,"h":75}},"sprite128":{"frame":{"x":1125,"y":525,"w":75,"h":75},"rotated":false,"trimmed":false,"spriteSourceSize":{"x":0,"y":0,"w":75,"h":75},"sourceSize":{"w":75,"h":75}},"sprite129":{"frame":{"x":0,"y":600,"w":75,"h":75},"rotated":false,"trimmed":false,"spriteSourceSize":{"x":0,"y":0,"w":75,"h":75},"sourceSize":{"w":75,"h":75}},"sprite130":{"frame":{"x":75,"y":600,"w":75,"h":75},"rotated":false,"trimmed":false,"spriteSourceSize":{"x":0,"y":0,"w":75,"h":75},"sourceSize":{"w":75,"h":75}},"sprite131":{"frame":{"x":150,"y":600,"w":75,"h":75},"rotated":false,"trimmed":false,"spriteSourceSize":{"x":0,"y":0,"w":75,"h":75},"sourceSize":{"w":75,"h":75}},"sprite132":{"frame":{"x":225,"y":600,"w":75,"h":75},"rotated":false,"trimmed":false,"spriteSourceSize":{"x":0,"y":0,"w":75,"h":75},"sourceSize":{"w":75,"h":75}},"sprite133":{"frame":{"x":300,"y":600,"w":75,"h":75},"rotated":false,"trimmed":false,"spriteSourceSize":{"x":0,"y":0,"w":75,"h":75},"sourceSize":{"w":75,"h":75}},"sprite134":{"frame":{"x":375,"y":600,"w":75,"h":75},"rotated":false,"trimmed":false,"spriteSourceSize":{"x":0,"y":0,"w":75,"h":75},"sourceSize":{"w":75,"h":75}},"sprite135":{"frame":{"x":450,"y":600,"w":75,"h":75},"rotated":false,"trimmed":false,"spriteSourceSize":{"x":0,"y":0,"w":75,"h":75},"sourceSize":{"w":75,"h":75}},"sprite136":{"frame":{"x":525,"y":600,"w":75,"h":75},"rotated":false,"trimmed":false,"spriteSourceSize":{"x":0,"y":0,"w":75,"h":75},"sourceSize":{"w":75,"h":75}},"sprite137":{"frame":{"x":600,"y":600,"w":75,"h":75},"rotated":false,"trimmed":false,"spriteSourceSize":{"x":0,"y":0,"w":75,"h":75},"sourceSize":{"w":75,"h":75}},"sprite138":{"frame":{"x":675,"y":600,"w":75,"h":75},"rotated":false,"trimmed":false,"spriteSourceSize":{"x":0,"y":0,"w":75,"h":75},"sourceSize":{"w":75,"h":75}},"sprite139":{"frame":{"x":750,"y":600,"w":75,"h":75},"rotated":false,"trimmed":false,"spriteSourceSize":{"x":0,"y":0,"w":75,"h":75},"sourceSize":{"w":75,"h":75}},"sprite140":{"frame":{"x":825,"y":600,"w":75,"h":75},"rotated":false,"trimmed":false,"spriteSourceSize":{"x":0,"y":0,"w":75,"h":75},"sourceSize":{"w":75,"h":75}},"sprite141":{"frame":{"x":900,"y":600,"w":75,"h":75},"rotated":false,"trimmed":false,"spriteSourceSize":{"x":0,"y":0,"w":75,"h":75},"sourceSize":{"w":75,"h":75}},"sprite142":{"frame":{"x":975,"y":600,"w":75,"h":75},"rotated":false,"trimmed":false,"spriteSourceSize":{"x":0,"y":0,"w":75,"h":75},"sourceSize":{"w":75,"h":75}},"sprite143":{"frame":{"x":1050,"y":600,"w":75,"h":75},"rotated":false,"trimmed":false,"spriteSourceSize":{"x":0,"y":0,"w":75,"h":75},"sourceSize":{"w":75,"h":75}},"sprite144":{"frame":{"x":1125,"y":600,"w":75,"h":75},"rotated":false,"trimmed":false,"spriteSourceSize":{"x":0,"y":0,"w":75,"h":75},"sourceSize":{"w":75,"h":75}},"sprite145":{"frame":{"x":0,"y":675,"w":75,"h":75},"rotated":false,"trimmed":false,"spriteSourceSize":{"x":0,"y":0,"w":75,"h":75},"sourceSize":{"w":75,"h":75}},"sprite146":{"frame":{"x":75,"y":675,"w":75,"h":75},"rotated":false,"trimmed":false,"spriteSourceSize":{"x":0,"y":0,"w":75,"h":75},"sourceSize":{"w":75,"h":75}},"sprite147":{"frame":{"x":150,"y":675,"w":75,"h":75},"rotated":false,"trimmed":false,"spriteSourceSize":{"x":0,"y":0,"w":75,"h":75},"sourceSize":{"w":75,"h":75}},"sprite148":{"frame":{"x":225,"y":675,"w":75,"h":75},"rotated":false,"trimmed":false,"spriteSourceSize":{"x":0,"y":0,"w":75,"h":75},"sourceSize":{"w":75,"h":75}},"sprite149":{"frame":{"x":300,"y":675,"w":75,"h":75},"rotated":false,"trimmed":false,"spriteSourceSize":{"x":0,"y":0,"w":75,"h":75},"sourceSize":{"w":75,"h":75}},"sprite150":{"frame":{"x":375,"y":675,"w":75,"h":75},"rotated":false,"trimmed":false,"spriteSourceSize":{"x":0,"y":0,"w":75,"h":75},"sourceSize":{"w":75,"h":75}},"sprite151":{"frame":{"x":450,"y":675,"w":75,"h":75},"rotated":false,"trimmed":false,"spriteSourceSize":{"x":0,"y":0,"w":75,"h":75},"sourceSize":{"w":75,"h":75}},"sprite152":{"frame":{"x":525,"y":675,"w":75,"h":75},"rotated":false,"trimmed":false,"spriteSourceSize":{"x":0,"y":0,"w":75,"h":75},"sourceSize":{"w":75,"h":75}},"sprite153":{"frame":{"x":600,"y":675,"w":75,"h":75},"rotated":false,"trimmed":false,"spriteSourceSize":{"x":0,"y":0,"w":75,"h":75},"sourceSize":{"w":75,"h":75}},"sprite154":{"frame":{"x":675,"y":675,"w":75,"h":75},"rotated":false,"trimmed":false,"spriteSourceSize":{"x":0,"y":0,"w":75,"h":75},"sourceSize":{"w":75,"h":75}},"sprite155":{"frame":{"x":750,"y":675,"w":75,"h":75},"rotated":false,"trimmed":false,"spriteSourceSize":{"x":0,"y":0,"w":75,"h":75},"sourceSize":{"w":75,"h":75}},"sprite156":{"frame":{"x":825,"y":675,"w":75,"h":75},"rotated":false,"trimmed":false,"spriteSourceSize":{"x":0,"y":0,"w":75,"h":75},"sourceSize":{"w":75,"h":75}},"sprite157":{"frame":{"x":900,"y":675,"w":75,"h":75},"rotated":false,"trimmed":false,"spriteSourceSize":{"x":0,"y":0,"w":75,"h":75},"sourceSize":{"w":75,"h":75}},"sprite158":{"frame":{"x":975,"y":675,"w":75,"h":75},"rotated":false,"trimmed":false,"spriteSourceSize":{"x":0,"y":0,"w":75,"h":75},"sourceSize":{"w":75,"h":75}},"sprite159":{"frame":{"x":1050,"y":675,"w":75,"h":75},"rotated":false,"trimmed":false,"spriteSourceSize":{"x":0,"y":0,"w":75,"h":75},"sourceSize":{"w":75,"h":75}},"sprite160":{"frame":{"x":1125,"y":675,"w":75,"h":75},"rotated":false,"trimmed":false,"spriteSourceSize":{"x":0,"y":0,"w":75,"h":75},"sourceSize":{"w":75,"h":75}}},"meta":{"app":"https://www.leshylabs.com/apps/sstool/","version":"Leshy SpriteSheet Tool v0.8.4","image":"spritesheet.png","size":{"w":1200,"h":750},"scale":1}}